autoqt.py
autoqt-0.0.6.dist-info/LICENSE
autoqt-0.0.6.dist-info/METADATA
autoqt-0.0.6.dist-info/WHEEL
autoqt-0.0.6.dist-info/top_level.txt
autoqt-0.0.6.dist-info/RECORD
