Metadata-Version: 2.1
Name: autoqt
Version: 0.0.6
Summary: Simplify pyqtProperty creation.
Home-page: https://github.com/chipolux/autoqt/
Author: NaKyle Wright
Author-email: nakyle.wright@gmail.com
License: UNKNOWN
Keywords: PyQt,PyQt5,pyqtProperty,PySide2
Platform: UNKNOWN
Classifier: Development Status :: 3 - Alpha
Classifier: Intended Audience :: Developers
Classifier: Operating System :: OS Independent
Classifier: Programming Language :: Python :: 3
Classifier: License :: OSI Approved :: MIT License
Classifier: Topic :: Software Development
Requires-Python: >=3.6
